<?xml version="1.0" encoding="utf-8" ?>
<dwsync>
<file name="screenshotProcess.php" server="31.170.166.145" local="130747464440000000" remote="130755901200000000" Dst="0" />
<file name="avatar.php" server="C:/xampp/htdocs/GS/" local="130749166300000000" remote="130749166300000000" Dst="0" />
<file name="createPost.php" server="C:/xampp/htdocs/GS/" local="130748765920000000" remote="130748765920000000" Dst="0" />
<file name="logout.php" server="C:/xampp/htdocs/GS/" local="130747456800000000" remote="130747456800000000" Dst="0" />
<file name="processDetails.php" server="C:/xampp/htdocs/GS/" local="130747457500000000" remote="130747457500000000" Dst="0" />
<file name="processlogin.php" server="C:/xampp/htdocs/GS/" local="130749186120000000" remote="130749186120000000" Dst="0" />
<file name="processregister - Copy.php" server="C:/xampp/htdocs/GS/" local="130755334280000000" remote="130755334280000000" Dst="0" />
<file name="processregister.php" server="C:/xampp/htdocs/GS/" local="130755360480000000" remote="130755360480000000" Dst="0" />
<file name="processUpdateProfile.php" server="C:/xampp/htdocs/GS/" local="130747453340000000" remote="130747453340000000" Dst="0" />
<file name="processX1_session.php" server="C:/xampp/htdocs/GS/" local="130747446660000000" remote="130747446660000000" Dst="0" />
<file name="screenshotProcess.php" server="C:/xampp/htdocs/GS/" local="130747464440000000" remote="130747464440000000" Dst="0" />
<file name="avatar.php" server="31.170.166.145" local="130749166300000000" remote="130755903000000000" Dst="0" />
<file name="createPost.php" server="31.170.166.145" local="130748765920000000" remote="130755903000000000" Dst="0" />
<file name="logout.php" server="31.170.166.145" local="130747456800000000" remote="130755903000000000" Dst="0" />
<file name="processDetails.php" server="31.170.166.145" local="130747457500000000" remote="130755903000000000" Dst="0" />
<file name="processlogin.php" server="31.170.166.145" local="130749186120000000" remote="130755903000000000" Dst="0" />
<file name="processregister - Copy.php" server="31.170.166.145" local="130755334280000000" remote="130755903000000000" Dst="0" />
<file name="processregister.php" server="31.170.166.145" local="130756471668263242" remote="130755974400000000" Dst="0" />
<file name="processUpdateProfile.php" server="31.170.166.145" local="130747453340000000" remote="130755903000000000" Dst="0" />
<file name="processX1_session.php" server="31.170.166.145" local="130747446660000000" remote="130755903000000000" Dst="0" />
<file name="addGamesProcess.php" server="31.170.166.145" local="130756474462413058" remote="130755974400000000" Dst="0" />
</dwsync>